[
  {
    "quarter": "Q4 2021",
    "period_end": "2021-12-31",
    "nav_per_share": 25.0,
    "nav_per_share_qoq_change": null,
    "net_assets_mn": 50.0,
    "total_investments_fv_mn": null,
    "total_debt_mn": null,
    "leverage": null,
    "nii_per_share": null,
    "dividend_per_share": null,
    "nii_coverage": null,
    "total_investment_income_mn": null,
    "net_investment_income_mn": null,
    "total_expenses_mn": null,
    "pik_pct": null,
    "weighted_avg_yield": null,
    "cost_of_debt_pct": null,
    "na_pct_cost": null,
    "na_pct_fv": null,
    "wtd_avg_risk_rating": null,
    "first_lien_pct": null,
    "second_lien_pct": null,
    "subordinated_pct": null,
    "equity_pct": null,
    "floating_rate_pct": null,
    "num_portfolio_companies": 150,
    "originations_mn": null,
    "repayments_mn": null,
    "net_unrealized_gains_mn": null,
    "realized_gain_loss_3mo_mn": null,
    "credit_facility_drawn_mn": null,
    "unused_capacity_mn": null,
    "price_to_nav": null,
    "total_return_index": 25.0,
    "data_quality_score": 12.5
  },
  {
    "quarter": "Q1 2022",
    "period_end": "2022-03-31",
    "nav_per_share": 24.71,
    "nav_per_share_qoq_change": -0.29,
    "net_assets_mn": 1311.45,
    "total_investments_fv_mn": 20.272,
    "total_debt_mn": 707.63,
    "leverage": 0.54,
    "nii_per_share": 0.24,
    "dividend_per_share": 0.25,
    "nii_coverage": 0.96,
    "total_investment_income_mn": 20.272,
    "net_investment_income_mn": 15.877,
    "total_expenses_mn": 10.751,
    "pik_pct": 4.46,
    "weighted_avg_yield": 5.31,
    "cost_of_debt_pct": 4.59,
    "na_pct_cost": null,
    "na_pct_fv": null,
    "wtd_avg_risk_rating": null,
    "first_lien_pct": null,
    "second_lien_pct": null,
    "subordinated_pct": null,
    "equity_pct": null,
    "floating_rate_pct": null,
    "num_portfolio_companies": 649,
    "originations_mn": 4118.58,
    "repayments_mn": 407.94,
    "net_unrealized_gains_mn": 13.09,
    "realized_gain_loss_3mo_mn": null,
    "credit_facility_drawn_mn": 1835.0,
    "unused_capacity_mn": null,
    "price_to_nav": null,
    "net_interest_spread": 0.72,
    "net_originations_mn": 3710.64,
    "total_return_index": 24.96,
    "avg_position_size_mn": 0.031,
    "cash_income_mn": 19.368,
    "cash_income_pct": 95.54,
    "origination_velocity_pct": 20316.594,
    "cumulative_dividends_paid": 0.25,
    "data_quality_score": 71.8
  },
  {
    "quarter": "Q2 2022",
    "period_end": "2022-06-30",
    "nav_per_share": 22.87,
    "nav_per_share_qoq_change": -1.84,
    "net_assets_mn": 1525.76,
    "total_investments_fv_mn": 46.873,
    "total_debt_mn": 1865.87,
    "leverage": 1.223,
    "nii_per_share": 0.37,
    "dividend_per_share": 0.31,
    "nii_coverage": 1.194,
    "total_investment_income_mn": 67.144,
    "net_investment_income_mn": 34.42,
    "total_expenses_mn": 23.501,
    "pik_pct": 2.38,
    "weighted_avg_yield": 7.69,
    "cost_of_debt_pct": 3.7,
    "na_pct_cost": null,
    "na_pct_fv": null,
    "wtd_avg_risk_rating": null,
    "first_lien_pct": 48.95,
    "second_lien_pct": null,
    "subordinated_pct": 1.05,
    "equity_pct": null,
    "floating_rate_pct": null,
    "num_portfolio_companies": 384,
    "originations_mn": 5745.83,
    "repayments_mn": 1220.35,
    "net_unrealized_gains_mn": -122.3,
    "realized_gain_loss_3mo_mn": null,
    "credit_facility_drawn_mn": 2085.0,
    "unused_capacity_mn": 1306.09,
    "price_to_nav": null,
    "net_interest_spread": 3.99,
    "net_originations_mn": 4525.48,
    "dividend_change_flag": 1,
    "total_return_index": 23.43,
    "liquidity_pct_of_portfolio": 2786.444,
    "avg_position_size_mn": 0.122,
    "cash_income_mn": 65.546,
    "cash_income_pct": 97.62,
    "origination_velocity_pct": 12258.294,
    "cumulative_dividends_paid": 0.56,
    "data_quality_score": 80.5
  },
  {
    "quarter": "Q3 2022",
    "period_end": "2022-09-30",
    "nav_per_share": 22.97,
    "nav_per_share_qoq_change": 0.1,
    "net_assets_mn": 1749.31,
    "total_investments_fv_mn": 78.468,
    "total_debt_mn": 2046.16,
    "leverage": 1.17,
    "nii_per_share": 0.4,
    "dividend_per_share": 0.33,
    "nii_coverage": 1.212,
    "total_investment_income_mn": 145.612,
    "net_investment_income_mn": 41.162,
    "total_expenses_mn": 38.058,
    "pik_pct": 2.14,
    "weighted_avg_yield": 9.3,
    "cost_of_debt_pct": 4.6,
    "na_pct_cost": null,
    "na_pct_fv": null,
    "wtd_avg_risk_rating": null,
    "first_lien_pct": null,
    "second_lien_pct": null,
    "subordinated_pct": null,
    "equity_pct": 100.0,
    "floating_rate_pct": null,
    "num_portfolio_companies": 910,
    "originations_mn": 6038.43,
    "repayments_mn": 1674.87,
    "net_unrealized_gains_mn": -4.92,
    "realized_gain_loss_3mo_mn": 0.0,
    "credit_facility_drawn_mn": 2085.0,
    "unused_capacity_mn": 1076.5,
    "price_to_nav": null,
    "net_interest_spread": 4.7,
    "net_originations_mn": 4363.56,
    "dividend_change_flag": 1,
    "total_return_index": 23.86,
    "liquidity_pct_of_portfolio": 1371.897,
    "avg_position_size_mn": 0.086,
    "cash_income_mn": 142.496,
    "cash_income_pct": 97.86,
    "origination_velocity_pct": 7695.404,
    "cumulative_dividends_paid": 0.89,
    "data_quality_score": 80.5
  },
  {
    "quarter": "Q4 2022",
    "period_end": "2022-12-31",
    "nav_per_share": 23.2,
    "nav_per_share_qoq_change": 0.23,
    "net_assets_mn": 1901.23,
    "total_investments_fv_mn": 4308.892,
    "total_debt_mn": 3835.0,
    "leverage": 2.017,
    "nii_per_share": null,
    "dividend_per_share": 0.33,
    "nii_coverage": null,
    "total_investment_income_mn": 252.301,
    "net_investment_income_mn": null,
    "total_expenses_mn": null,
    "pik_pct": null,
    "weighted_avg_yield": 10.8,
    "cost_of_debt_pct": 6.05,
    "na_pct_cost": null,
    "na_pct_fv": null,
    "wtd_avg_risk_rating": null,
    "first_lien_pct": null,
    "second_lien_pct": null,
    "subordinated_pct": null,
    "equity_pct": 100.0,
    "floating_rate_pct": null,
    "num_portfolio_companies": 190,
    "originations_mn": 9207.28,
    "repayments_mn": 1132.92,
    "net_unrealized_gains_mn": null,
    "realized_gain_loss_3mo_mn": null,
    "credit_facility_drawn_mn": 2085.0,
    "unused_capacity_mn": null,
    "price_to_nav": null,
    "net_interest_spread": 4.75,
    "net_originations_mn": 8074.36,
    "dividend_change_flag": 0,
    "total_return_index": 24.42,
    "avg_position_size_mn": 22.678,
    "nav_per_share_yoy_growth_pct": -7.2,
    "origination_velocity_pct": 213.681,
    "cumulative_dividends_paid": 1.22,
    "data_quality_score": 59.0
  },
  {
    "quarter": "Q1 2023",
    "period_end": "2023-03-31",
    "nav_per_share": 23.82,
    "nav_per_share_qoq_change": 0.62,
    "net_assets_mn": 1982.27,
    "total_investments_fv_mn": 4252.936,
    "total_debt_mn": 3835.0,
    "leverage": 1.935,
    "nii_per_share": 0.56,
    "dividend_per_share": 0.47,
    "nii_coverage": 1.191,
    "total_investment_income_mn": 118.412,
    "net_investment_income_mn": 59.318,
    "total_expenses_mn": 57.633,
    "pik_pct": 0.77,
    "weighted_avg_yield": 11.2,
    "cost_of_debt_pct": 7.58,
    "na_pct_cost": null,
    "na_pct_fv": null,
    "wtd_avg_risk_rating": null,
    "first_lien_pct": null,
    "second_lien_pct": null,
    "subordinated_pct": null,
    "equity_pct": 99.0,
    "floating_rate_pct": null,
    "num_portfolio_companies": 649,
    "originations_mn": 655.05,
    "repayments_mn": 736.03,
    "net_unrealized_gains_mn": 52.45,
    "realized_gain_loss_3mo_mn": null,
    "credit_facility_drawn_mn": 2085.0,
    "unused_capacity_mn": 561.14,
    "price_to_nav": null,
    "net_interest_spread": 3.62,
    "net_originations_mn": -80.98,
    "dividend_change_flag": 1,
    "total_return_index": 25.51,
    "liquidity_pct_of_portfolio": 13.194,
    "avg_position_size_mn": 6.553,
    "cash_income_mn": 117.5,
    "cash_income_pct": 99.23,
    "nii_per_share_yoy_growth_pct": 133.333,
    "nav_per_share_yoy_growth_pct": -3.602,
    "origination_velocity_pct": 15.402,
    "cumulative_dividends_paid": 1.69,
    "data_quality_score": 79.1
  },
  {
    "quarter": "Q2 2023",
    "period_end": "2023-06-30",
    "nav_per_share": 24.18,
    "nav_per_share_qoq_change": 0.36,
    "net_assets_mn": 2230.37,
    "total_investments_fv_mn": 4770.043,
    "total_debt_mn": 3835.0,
    "leverage": 1.719,
    "nii_per_share": 0.58,
    "dividend_per_share": 0.48,
    "nii_coverage": 1.208,
    "total_investment_income_mn": 248.613,
    "net_investment_income_mn": 69.383,
    "total_expenses_mn": 59.34,
    "pik_pct": 2.17,
    "weighted_avg_yield": 11.4,
    "cost_of_debt_pct": 8.34,
    "na_pct_cost": null,
    "na_pct_fv": null,
    "wtd_avg_risk_rating": null,
    "first_lien_pct": null,
    "second_lien_pct": null,
    "subordinated_pct": null,
    "equity_pct": 99.0,
    "floating_rate_pct": null,
    "num_portfolio_companies": 384,
    "originations_mn": 1446.45,
    "repayments_mn": 1065.35,
    "net_unrealized_gains_mn": 31.28,
    "realized_gain_loss_3mo_mn": null,
    "credit_facility_drawn_mn": 2085.0,
    "unused_capacity_mn": 819.68,
    "price_to_nav": null,
    "net_interest_spread": 3.06,
    "net_originations_mn": 381.1,
    "dividend_change_flag": 1,
    "total_return_index": 26.35,
    "liquidity_pct_of_portfolio": 17.184,
    "avg_position_size_mn": 12.422,
    "cash_income_mn": 243.218,
    "cash_income_pct": 97.83,
    "nii_per_share_yoy_growth_pct": 56.757,
    "nav_per_share_yoy_growth_pct": 5.728,
    "origination_velocity_pct": 30.324,
    "cumulative_dividends_paid": 2.17,
    "data_quality_score": 79.1
  },
  {
    "quarter": "Q3 2023",
    "period_end": "2023-09-30",
    "nav_per_share": 24.55,
    "nav_per_share_qoq_change": 0.37,
    "net_assets_mn": 2651.04,
    "total_investments_fv_mn": 5287.232,
    "total_debt_mn": 4481.15,
    "leverage": 1.69,
    "nii_per_share": 0.59,
    "dividend_per_share": 0.4833,
    "nii_coverage": 1.221,
    "total_investment_income_mn": 396.726,
    "net_investment_income_mn": 79.567,
    "total_expenses_mn": 67.052,
    "pik_pct": 2.01,
    "weighted_avg_yield": 11.3,
    "cost_of_debt_pct": 7.8,
    "na_pct_cost": null,
    "na_pct_fv": null,
    "wtd_avg_risk_rating": null,
    "first_lien_pct": null,
    "second_lien_pct": null,
    "subordinated_pct": null,
    "equity_pct": 100.0,
    "floating_rate_pct": null,
    "num_portfolio_companies": 910,
    "originations_mn": 2318.18,
    "repayments_mn": 1441.36,
    "net_unrealized_gains_mn": 24.27,
    "realized_gain_loss_3mo_mn": null,
    "credit_facility_drawn_mn": 2085.0,
    "unused_capacity_mn": 383.87,
    "price_to_nav": null,
    "net_interest_spread": 3.5,
    "net_originations_mn": 876.82,
    "dividend_change_flag": 1,
    "total_return_index": 27.2033,
    "liquidity_pct_of_portfolio": 7.26,
    "avg_position_size_mn": 5.81,
    "cash_income_mn": 388.752,
    "cash_income_pct": 97.99,
    "nii_per_share_yoy_growth_pct": 47.5,
    "nav_per_share_yoy_growth_pct": 6.879,
    "origination_velocity_pct": 43.845,
    "cumulative_dividends_paid": 2.6533,
    "data_quality_score": 79.1
  },
  {
    "quarter": "Q4 2023",
    "period_end": "2023-12-31",
    "nav_per_share": 24.63,
    "nav_per_share_qoq_change": 0.08,
    "net_assets_mn": 3265.05,
    "total_investments_fv_mn": 6719.588,
    "total_debt_mn": 4705.36,
    "leverage": 1.441,
    "nii_per_share": null,
    "dividend_per_share": 0.4833,
    "nii_coverage": null,
    "total_investment_income_mn": 586.832,
    "net_investment_income_mn": null,
    "total_expenses_mn": null,
    "pik_pct": null,
    "weighted_avg_yield": 11.6,
    "cost_of_debt_pct": 8.23,
    "na_pct_cost": 0.1,
    "na_pct_fv": 0.1,
    "wtd_avg_risk_rating": null,
    "first_lien_pct": null,
    "second_lien_pct": null,
    "subordinated_pct": null,
    "equity_pct": 99.0,
    "floating_rate_pct": null,
    "num_portfolio_companies": 535,
    "originations_mn": 116.33,
    "repayments_mn": 1334.3,
    "net_unrealized_gains_mn": null,
    "realized_gain_loss_3mo_mn": null,
    "credit_facility_drawn_mn": 2185.0,
    "unused_capacity_mn": null,
    "price_to_nav": null,
    "net_interest_spread": 3.37,
    "net_originations_mn": -1217.97,
    "dividend_change_flag": 0,
    "total_return_index": 27.7666,
    "avg_position_size_mn": 12.56,
    "na_dollar_amount_mn": 6.72,
    "implied_recovery_rate_pct": 0.0,
    "nav_per_share_yoy_growth_pct": 6.164,
    "origination_velocity_pct": 1.731,
    "cumulative_dividends_paid": 3.1366,
    "data_quality_score": 65.9
  },
  {
    "quarter": "Q1 2024",
    "period_end": "2024-03-31",
    "nav_per_share": 24.85,
    "nav_per_share_qoq_change": 0.22,
    "net_assets_mn": 4169.43,
    "total_investments_fv_mn": 8474.656,
    "total_debt_mn": 5533.1,
    "leverage": 1.327,
    "nii_per_share": 0.6,
    "dividend_per_share": 0.55,
    "nii_coverage": 1.091,
    "total_investment_income_mn": 224.695,
    "net_investment_income_mn": 128.39,
    "total_expenses_mn": 96.305,
    "pik_pct": 2.32,
    "weighted_avg_yield": null,
    "cost_of_debt_pct": 8.7,
    "na_pct_cost": 0.1,
    "na_pct_fv": 0.0,
    "wtd_avg_risk_rating": null,
    "first_lien_pct": null,
    "second_lien_pct": null,
    "subordinated_pct": null,
    "equity_pct": 99.0,
    "floating_rate_pct": null,
    "num_portfolio_companies": 480,
    "originations_mn": 2337.68,
    "repayments_mn": 458.11,
    "net_unrealized_gains_mn": 63.61,
    "realized_gain_loss_3mo_mn": null,
    "credit_facility_drawn_mn": 2185.0,
    "unused_capacity_mn": 102.0,
    "price_to_nav": null,
    "net_originations_mn": 1879.57,
    "dividend_change_flag": 1,
    "total_return_index": 28.5366,
    "liquidity_pct_of_portfolio": 1.204,
    "avg_position_size_mn": 17.656,
    "na_dollar_amount_mn": 8.475,
    "implied_recovery_rate_pct": 100.0,
    "cash_income_mn": 219.482,
    "cash_income_pct": 97.68,
    "nii_per_share_yoy_growth_pct": 7.143,
    "nav_per_share_yoy_growth_pct": 4.324,
    "origination_velocity_pct": 27.584,
    "cumulative_dividends_paid": 3.6866,
    "data_quality_score": 81.8
  },
  {
    "quarter": "Q2 2024",
    "period_end": "2024-06-30",
    "nav_per_share": 24.9,
    "nav_per_share_qoq_change": 0.05,
    "net_assets_mn": 5385.43,
    "total_investments_fv_mn": 11033.07,
    "total_debt_mn": 5532.39,
    "leverage": 1.027,
    "nii_per_share": 0.6,
    "dividend_per_share": 0.55,
    "nii_coverage": 1.091,
    "total_investment_income_mn": 506.413,
    "net_investment_income_mn": 161.304,
    "total_expenses_mn": 120.415,
    "pik_pct": 1.37,
    "weighted_avg_yield": null,
    "cost_of_debt_pct": 8.6,
    "na_pct_cost": 0.1,
    "na_pct_fv": 0.0,
    "wtd_avg_risk_rating": null,
    "first_lien_pct": null,
    "second_lien_pct": null,
    "subordinated_pct": null,
    "equity_pct": 99.0,
    "floating_rate_pct": null,
    "num_portfolio_companies": 796,
    "originations_mn": 5833.49,
    "repayments_mn": 1268.23,
    "net_unrealized_gains_mn": -10.91,
    "realized_gain_loss_3mo_mn": null,
    "credit_facility_drawn_mn": 2185.0,
    "unused_capacity_mn": 1708.38,
    "price_to_nav": null,
    "net_originations_mn": 4565.26,
    "dividend_change_flag": 0,
    "total_return_index": 29.1366,
    "liquidity_pct_of_portfolio": 15.484,
    "avg_position_size_mn": 13.861,
    "na_dollar_amount_mn": 11.033,
    "implied_recovery_rate_pct": 100.0,
    "cash_income_mn": 499.475,
    "cash_income_pct": 98.63,
    "nii_per_share_yoy_growth_pct": 3.448,
    "nav_per_share_yoy_growth_pct": 2.978,
    "origination_velocity_pct": 52.873,
    "cumulative_dividends_paid": 4.2366,
    "data_quality_score": 81.8
  },
  {
    "quarter": "Q3 2024",
    "period_end": "2024-09-30",
    "nav_per_share": 24.94,
    "nav_per_share_qoq_change": 0.04,
    "net_assets_mn": 6454.42,
    "total_investments_fv_mn": 12413.755,
    "total_debt_mn": 6861.18,
    "leverage": 1.063,
    "nii_per_share": 0.59,
    "dividend_per_share": null,
    "nii_coverage": null,
    "total_investment_income_mn": 853.496,
    "net_investment_income_mn": 195.601,
    "total_expenses_mn": 151.482,
    "pik_pct": 1.07,
    "weighted_avg_yield": null,
    "cost_of_debt_pct": 8.0,
    "na_pct_cost": 0.7,
    "na_pct_fv": 0.3,
    "wtd_avg_risk_rating": null,
    "first_lien_pct": null,
    "second_lien_pct": null,
    "subordinated_pct": null,
    "equity_pct": 99.0,
    "floating_rate_pct": null,
    "num_portfolio_companies": 831,
    "originations_mn": 8455.83,
    "repayments_mn": 2711.28,
    "net_unrealized_gains_mn": 29.22,
    "realized_gain_loss_3mo_mn": null,
    "credit_facility_drawn_mn": 2185.0,
    "unused_capacity_mn": 778.61,
    "price_to_nav": null,
    "net_originations_mn": 5744.55,
    "total_return_index": 29.1766,
    "liquidity_pct_of_portfolio": 6.272,
    "avg_position_size_mn": 14.938,
    "na_dollar_amount_mn": 86.896,
    "implied_recovery_rate_pct": 57.143,
    "cash_income_mn": 844.364,
    "cash_income_pct": 98.93,
    "nii_per_share_yoy_growth_pct": 0.0,
    "nav_per_share_yoy_growth_pct": 1.589,
    "origination_velocity_pct": 68.117,
    "cumulative_dividends_paid": 4.2366,
    "data_quality_score": 76.7
  },
  {
    "quarter": "Q4 2024",
    "period_end": "2024-12-31",
    "nav_per_share": 24.86,
    "nav_per_share_qoq_change": -0.08,
    "net_assets_mn": 7502.61,
    "total_investments_fv_mn": 14555.535,
    "total_debt_mn": 7584.23,
    "leverage": 1.011,
    "nii_per_share": null,
    "dividend_per_share": null,
    "nii_coverage": null,
    "total_investment_income_mn": 1206.384,
    "net_investment_income_mn": null,
    "total_expenses_mn": null,
    "pik_pct": null,
    "weighted_avg_yield": 10.6,
    "cost_of_debt_pct": 8.25,
    "na_pct_cost": 0.6,
    "na_pct_fv": 0.2,
    "wtd_avg_risk_rating": null,
    "first_lien_pct": null,
    "second_lien_pct": null,
    "subordinated_pct": 96.0,
    "equity_pct": null,
    "floating_rate_pct": null,
    "num_portfolio_companies": 455,
    "originations_mn": 4976.68,
    "repayments_mn": 861.73,
    "net_unrealized_gains_mn": null,
    "realized_gain_loss_3mo_mn": null,
    "credit_facility_drawn_mn": 2740.0,
    "unused_capacity_mn": null,
    "price_to_nav": null,
    "net_interest_spread": 2.35,
    "net_originations_mn": 4114.95,
    "total_return_index": 29.0966,
    "avg_position_size_mn": 31.99,
    "na_dollar_amount_mn": 87.333,
    "implied_recovery_rate_pct": 66.667,
    "nav_per_share_yoy_growth_pct": 0.934,
    "origination_velocity_pct": 34.191,
    "cumulative_dividends_paid": 4.2366,
    "data_quality_score": 62.5
  },
  {
    "quarter": "Q1 2025",
    "period_end": "2025-03-31",
    "nav_per_share": 24.65,
    "nav_per_share_qoq_change": -0.21,
    "net_assets_mn": 9006.55,
    "total_investments_fv_mn": 17428.014,
    "total_debt_mn": 8728.32,
    "leverage": 0.969,
    "nii_per_share": 0.47,
    "dividend_per_share": null,
    "nii_coverage": null,
    "total_investment_income_mn": 392.771,
    "net_investment_income_mn": 224.03,
    "total_expenses_mn": 168.741,
    "pik_pct": 1.34,
    "weighted_avg_yield": 9.34,
    "cost_of_debt_pct": 7.1,
    "na_pct_cost": 0.8,
    "na_pct_fv": 0.2,
    "wtd_avg_risk_rating": null,
    "first_lien_pct": null,
    "second_lien_pct": null,
    "subordinated_pct": 96.0,
    "equity_pct": null,
    "floating_rate_pct": null,
    "num_portfolio_companies": 655,
    "originations_mn": 4690.11,
    "repayments_mn": 1305.05,
    "net_unrealized_gains_mn": -1.45,
    "realized_gain_loss_3mo_mn": null,
    "credit_facility_drawn_mn": 2740.0,
    "unused_capacity_mn": 1015.43,
    "price_to_nav": null,
    "net_interest_spread": 2.24,
    "net_originations_mn": 3385.06,
    "total_return_index": 28.8866,
    "liquidity_pct_of_portfolio": 5.826,
    "avg_position_size_mn": 26.608,
    "na_dollar_amount_mn": 139.424,
    "implied_recovery_rate_pct": 75.0,
    "cash_income_mn": 387.508,
    "cash_income_pct": 98.66,
    "nii_per_share_yoy_growth_pct": -21.667,
    "nav_per_share_yoy_growth_pct": -0.805,
    "origination_velocity_pct": 26.911,
    "cumulative_dividends_paid": 4.2366,
    "data_quality_score": 79.5
  },
  {
    "quarter": "Q2 2025",
    "period_end": "2025-06-30",
    "nav_per_share": 24.6,
    "nav_per_share_qoq_change": -0.05,
    "net_assets_mn": 10507.09,
    "total_investments_fv_mn": 19896.145,
    "total_debt_mn": 9077.02,
    "leverage": 0.864,
    "nii_per_share": 0.47,
    "dividend_per_share": null,
    "nii_coverage": null,
    "total_investment_income_mn": 849.296,
    "net_investment_income_mn": 258.082,
    "total_expenses_mn": 198.442,
    "pik_pct": 2.02,
    "weighted_avg_yield": null,
    "cost_of_debt_pct": 7.3,
    "na_pct_cost": 0.5,
    "na_pct_fv": 0.2,
    "wtd_avg_risk_rating": null,
    "first_lien_pct": null,
    "second_lien_pct": null,
    "subordinated_pct": 96.0,
    "equity_pct": null,
    "floating_rate_pct": null,
    "num_portfolio_companies": 239,
    "originations_mn": 9592.3,
    "repayments_mn": 3959.34,
    "net_unrealized_gains_mn": 186.98,
    "realized_gain_loss_3mo_mn": null,
    "credit_facility_drawn_mn": 2740.0,
    "unused_capacity_mn": 975.69,
    "price_to_nav": null,
    "net_originations_mn": 5632.96,
    "total_return_index": 28.8366,
    "liquidity_pct_of_portfolio": 4.904,
    "avg_position_size_mn": 83.247,
    "na_dollar_amount_mn": 99.481,
    "implied_recovery_rate_pct": 60.0,
    "cash_income_mn": 832.14,
    "cash_income_pct": 97.98,
    "nii_per_share_yoy_growth_pct": -21.667,
    "nav_per_share_yoy_growth_pct": -1.205,
    "origination_velocity_pct": 48.212,
    "cumulative_dividends_paid": 4.2366,
    "data_quality_score": 76.7
  },
  {
    "quarter": "Q3 2025",
    "period_end": "2025-09-30",
    "nav_per_share": 24.52,
    "nav_per_share_qoq_change": -0.08,
    "net_assets_mn": 11469.36,
    "total_investments_fv_mn": 22491.891,
    "total_debt_mn": 8208.45,
    "leverage": 0.716,
    "nii_per_share": 0.45,
    "dividend_per_share": null,
    "nii_coverage": null,
    "total_investment_income_mn": 1350.86,
    "net_investment_income_mn": 276.625,
    "total_expenses_mn": 224.939,
    "pik_pct": 2.74,
    "weighted_avg_yield": null,
    "cost_of_debt_pct": 7.1,
    "na_pct_cost": 0.7,
    "na_pct_fv": 0.3,
    "wtd_avg_risk_rating": null,
    "first_lien_pct": null,
    "second_lien_pct": null,
    "subordinated_pct": 96.0,
    "equity_pct": null,
    "floating_rate_pct": 97.0,
    "num_portfolio_companies": 646,
    "originations_mn": 13649.81,
    "repayments_mn": 4978.73,
    "net_unrealized_gains_mn": 25.53,
    "realized_gain_loss_3mo_mn": null,
    "credit_facility_drawn_mn": 3453.0,
    "unused_capacity_mn": 1558.9,
    "price_to_nav": null,
    "net_originations_mn": 8671.08,
    "total_return_index": 28.7566,
    "liquidity_pct_of_portfolio": 6.931,
    "avg_position_size_mn": 34.817,
    "fixed_rate_pct": 3.0,
    "na_dollar_amount_mn": 157.443,
    "implied_recovery_rate_pct": 57.143,
    "cash_income_mn": 1313.846,
    "cash_income_pct": 97.26,
    "nii_per_share_yoy_growth_pct": -23.729,
    "nav_per_share_yoy_growth_pct": -1.684,
    "origination_velocity_pct": 60.688,
    "cumulative_dividends_paid": 4.2366,
    "data_quality_score": 79.5
  },
  {
    "quarter": "Q4 2025",
    "period_end": "2025-12-31",
    "nav_per_share": 24.4,
    "nav_per_share_qoq_change": -0.12,
    "net_assets_mn": 11836.7,
    "total_investments_fv_mn": 24515.628,
    "total_debt_mn": 7584.23,
    "leverage": 0.641,
    "nii_per_share": null,
    "dividend_per_share": null,
    "nii_coverage": null,
    "total_investment_income_mn": 1918.564,
    "net_investment_income_mn": null,
    "total_expenses_mn": null,
    "pik_pct": null,
    "weighted_avg_yield": 8.6,
    "cost_of_debt_pct": 6.94,
    "na_pct_cost": 0.8,
    "na_pct_fv": 0.3,
    "wtd_avg_risk_rating": null,
    "first_lien_pct": 99.8,
    "second_lien_pct": 2.0,
    "subordinated_pct": 1.0,
    "equity_pct": 7.0,
    "floating_rate_pct": 90.0,
    "num_portfolio_companies": 355,
    "originations_mn": 10103.44,
    "repayments_mn": 2233.84,
    "net_unrealized_gains_mn": null,
    "realized_gain_loss_3mo_mn": null,
    "credit_facility_drawn_mn": 3453.0,
    "unused_capacity_mn": 272.2,
    "price_to_nav": null,
    "net_interest_spread": 1.66,
    "net_originations_mn": 7869.6,
    "total_return_index": 28.6366,
    "liquidity_pct_of_portfolio": 1.11,
    "avg_position_size_mn": 69.058,
    "fixed_rate_pct": 10.0,
    "na_dollar_amount_mn": 196.125,
    "implied_recovery_rate_pct": 62.5,
    "nav_per_share_yoy_growth_pct": -1.85,
    "origination_velocity_pct": 41.212,
    "cumulative_dividends_paid": 4.2366,
    "data_quality_score": 76.2
  }
]