{
  "ticker": "MAIN",
  "last_updated": "2026-05-30T03:07:55Z",
  "count": 115,
  "items": [
    {
      "date": "2026-05-07",
      "title": "8-K \u2014 Results of Operations \u00b7 Financial Statements and Exhibits",
      "headline_ai": "",
      "snippet": "",
      "url": "https://www.sec.gov/Archives/edgar/data/1396440/000139644026000068/main-20260507.htm",
      "source": "edgar",
      "source_label": "SEC 8-K",
      "category": "earnings",
      "accession": "0001396440-26-000068"
    },
    {
      "date": "2026-05-06",
      "title": "8-K \u2014 Submission of Matters to a Vote",
      "headline_ai": "",
      "snippet": "",
      "url": "https://www.sec.gov/Archives/edgar/data/1396440/000139644026000066/main-20260504.htm",
      "source": "edgar",
      "source_label": "SEC 8-K",
      "category": "other",
      "accession": "0001396440-26-000066"
    },
    {
      "date": "2026-05-05",
      "title": "8-K \u2014 Other Events \u00b7 Financial Statements and Exhibits",
      "headline_ai": "",
      "snippet": "",
      "url": "https://www.sec.gov/Archives/edgar/data/1396440/000139644026000060/main-20260505.htm",
      "source": "edgar",
      "source_label": "SEC 8-K",
      "category": "other",
      "accession": "0001396440-26-000060"
    },
    {
      "date": "2026-04-16",
      "title": "8-K \u2014 Results of Operations \u00b7 Financial Statements and Exhibits",
      "headline_ai": "",
      "snippet": "",
      "url": "https://www.sec.gov/Archives/edgar/data/1396440/000139644026000058/main-20260416.htm",
      "source": "edgar",
      "source_label": "SEC 8-K",
      "category": "earnings",
      "accession": "0001396440-26-000058"
    },
    {
      "date": "2026-04-09",
      "title": "8-K \u2014 Material Definitive Agreement \u00b7 Material Off-Balance-Sheet Obligation \u00b7 Other Events \u00b7 Financial Statements and Exhibits",
      "headline_ai": "",
      "snippet": "",
      "url": "https://www.sec.gov/Archives/edgar/data/1396440/000139644026000055/main-20260408.htm",
      "source": "edgar",
      "source_label": "SEC 8-K",
      "category": "capital-markets",
      "accession": "0001396440-26-000055"
    },
    {
      "date": "2026-04-09",
      "title": "8-K \u2014 Results of Operations \u00b7 Financial Statements and Exhibits",
      "headline_ai": "",
      "snippet": "",
      "url": "https://www.sec.gov/Archives/edgar/data/1396440/000139644026000051/main-20260409.htm",
      "source": "edgar",
      "source_label": "SEC 8-K",
      "category": "earnings",
      "accession": "0001396440-26-000051"
    },
    {
      "date": "2026-03-31",
      "title": "8-K \u2014 Material Definitive Agreement \u00b7 Material Off-Balance-Sheet Obligation \u00b7 Financial Statements and Exhibits",
      "headline_ai": "",
      "snippet": "",
      "url": "https://www.sec.gov/Archives/edgar/data/1396440/000139644026000046/main-20260327.htm",
      "source": "edgar",
      "source_label": "SEC 8-K",
      "category": "capital-markets",
      "accession": "0001396440-26-000046"
    },
    {
      "date": "2026-02-26",
      "title": "8-K \u2014 Results of Operations \u00b7 Financial Statements and Exhibits",
      "headline_ai": "",
      "snippet": "",
      "url": "https://www.sec.gov/Archives/edgar/data/1396440/000139644026000012/main-20260226.htm",
      "source": "edgar",
      "source_label": "SEC 8-K",
      "category": "earnings",
      "accession": "0001396440-26-000012"
    },
    {
      "date": "2026-02-24",
      "title": "8-K \u2014 Other Events \u00b7 Financial Statements and Exhibits",
      "headline_ai": "",
      "snippet": "",
      "url": "https://www.sec.gov/Archives/edgar/data/1396440/000139644026000009/main-20260224.htm",
      "source": "edgar",
      "source_label": "SEC 8-K",
      "category": "other",
      "accession": "0001396440-26-000009"
    },
    {
      "date": "2026-01-15",
      "title": "8-K \u2014 Results of Operations \u00b7 Financial Statements and Exhibits",
      "headline_ai": "",
      "snippet": "",
      "url": "https://www.sec.gov/Archives/edgar/data/1396440/000139644026000005/main-20260115.htm",
      "source": "edgar",
      "source_label": "SEC 8-K",
      "category": "earnings",
      "accession": "0001396440-26-000005"
    },
    {
      "date": "2026-01-08",
      "title": "8-K \u2014 Results of Operations \u00b7 Financial Statements and Exhibits",
      "headline_ai": "",
      "snippet": "",
      "url": "https://www.sec.gov/Archives/edgar/data/1396440/000139644026000003/main-20260108.htm",
      "source": "edgar",
      "source_label": "SEC 8-K",
      "category": "earnings",
      "accession": "0001396440-26-000003"
    },
    {
      "date": "2025-11-12",
      "title": "8-K \u2014 Material Definitive Agreement \u00b7 Financial Statements and Exhibits",
      "headline_ai": "",
      "snippet": "",
      "url": "https://www.sec.gov/Archives/edgar/data/1396440/000139644025000191/main-20251112.htm",
      "source": "edgar",
      "source_label": "SEC 8-K",
      "category": "capital-markets",
      "accession": "0001396440-25-000191"
    },
    {
      "date": "2025-11-07",
      "title": "8-K \u2014 Results of Operations \u00b7 Financial Statements and Exhibits",
      "headline_ai": "",
      "snippet": "",
      "url": "https://www.sec.gov/Archives/edgar/data/1396440/000139644025000179/main-20251106.htm",
      "source": "edgar",
      "source_label": "SEC 8-K",
      "category": "earnings",
      "accession": "0001396440-25-000179"
    },
    {
      "date": "2025-11-04",
      "title": "8-K \u2014 Other Events \u00b7 Financial Statements and Exhibits",
      "headline_ai": "",
      "snippet": "",
      "url": "https://www.sec.gov/Archives/edgar/data/1396440/000139644025000174/main-20251104.htm",
      "source": "edgar",
      "source_label": "SEC 8-K",
      "category": "other",
      "accession": "0001396440-25-000174"
    },
    {
      "date": "2025-10-14",
      "title": "8-K \u2014 Results of Operations \u00b7 Financial Statements and Exhibits",
      "headline_ai": "",
      "snippet": "",
      "url": "https://www.sec.gov/Archives/edgar/data/1396440/000139644025000167/main-20251014.htm",
      "source": "edgar",
      "source_label": "SEC 8-K",
      "category": "earnings",
      "accession": "0001396440-25-000167"
    },
    {
      "date": "2025-10-09",
      "title": "8-K \u2014 Results of Operations \u00b7 Financial Statements and Exhibits",
      "headline_ai": "",
      "snippet": "",
      "url": "https://www.sec.gov/Archives/edgar/data/1396440/000139644025000165/main-20251009.htm",
      "source": "edgar",
      "source_label": "SEC 8-K",
      "category": "earnings",
      "accession": "0001396440-25-000165"
    },
    {
      "date": "2025-09-26",
      "title": "8-K \u2014 Other Events",
      "headline_ai": "",
      "snippet": "",
      "url": "https://www.sec.gov/Archives/edgar/data/1396440/000139644025000159/main-20250926.htm",
      "source": "edgar",
      "source_label": "SEC 8-K",
      "category": "other",
      "accession": "0001396440-25-000159"
    },
    {
      "date": "2025-08-15",
      "title": "8-K \u2014 Material Definitive Agreement \u00b7 Material Off-Balance-Sheet Obligation \u00b7 Financial Statements and Exhibits",
      "headline_ai": "",
      "snippet": "",
      "url": "https://www.sec.gov/Archives/edgar/data/1396440/000139644025000151/main-20250813.htm",
      "source": "edgar",
      "source_label": "SEC 8-K",
      "category": "capital-markets",
      "accession": "0001396440-25-000151"
    },
    {
      "date": "2025-08-07",
      "title": "8-K \u2014 Results of Operations \u00b7 Financial Statements and Exhibits",
      "headline_ai": "",
      "snippet": "",
      "url": "https://www.sec.gov/Archives/edgar/data/1396440/000139644025000096/main-20250807.htm",
      "source": "edgar",
      "source_label": "SEC 8-K",
      "category": "earnings",
      "accession": "0001396440-25-000096"
    },
    {
      "date": "2025-08-05",
      "title": "8-K \u2014 Other Events \u00b7 Financial Statements and Exhibits",
      "headline_ai": "",
      "snippet": "",
      "url": "https://www.sec.gov/Archives/edgar/data/1396440/000139644025000094/main-20250805.htm",
      "source": "edgar",
      "source_label": "SEC 8-K",
      "category": "other",
      "accession": "0001396440-25-000094"
    },
    {
      "date": "2025-07-17",
      "title": "8-K \u2014 Results of Operations \u00b7 Financial Statements and Exhibits",
      "headline_ai": "",
      "snippet": "",
      "url": "https://www.sec.gov/Archives/edgar/data/1396440/000139644025000092/main-20250717.htm",
      "source": "edgar",
      "source_label": "SEC 8-K",
      "category": "earnings",
      "accession": "0001396440-25-000092"
    },
    {
      "date": "2025-07-10",
      "title": "8-K \u2014 Results of Operations \u00b7 Financial Statements and Exhibits",
      "headline_ai": "",
      "snippet": "",
      "url": "https://www.sec.gov/Archives/edgar/data/1396440/000139644025000090/main-20250710.htm",
      "source": "edgar",
      "source_label": "SEC 8-K",
      "category": "earnings",
      "accession": "0001396440-25-000090"
    },
    {
      "date": "2025-06-05",
      "title": "8-K \u2014 Regulation FD Disclosure",
      "headline_ai": "",
      "snippet": "",
      "url": "https://www.sec.gov/Archives/edgar/data/1396440/000139644025000087/main-20250605.htm",
      "source": "edgar",
      "source_label": "SEC 8-K",
      "category": "other",
      "accession": "0001396440-25-000087"
    },
    {
      "date": "2025-05-08",
      "title": "8-K \u2014 Results of Operations \u00b7 Financial Statements and Exhibits",
      "headline_ai": "",
      "snippet": "",
      "url": "https://www.sec.gov/Archives/edgar/data/1396440/000139644025000064/main-20250508.htm",
      "source": "edgar",
      "source_label": "SEC 8-K",
      "category": "earnings",
      "accession": "0001396440-25-000064"
    },
    {
      "date": "2025-05-06",
      "title": "8-K \u2014 Other Events \u00b7 Financial Statements and Exhibits",
      "headline_ai": "",
      "snippet": "",
      "url": "https://www.sec.gov/Archives/edgar/data/1396440/000139644025000060/main-20250506.htm",
      "source": "edgar",
      "source_label": "SEC 8-K",
      "category": "other",
      "accession": "0001396440-25-000060"
    },
    {
      "date": "2025-05-06",
      "title": "8-K \u2014 Submission of Matters to a Vote",
      "headline_ai": "",
      "snippet": "",
      "url": "https://www.sec.gov/Archives/edgar/data/1396440/000139644025000057/main-20250505.htm",
      "source": "edgar",
      "source_label": "SEC 8-K",
      "category": "other",
      "accession": "0001396440-25-000057"
    },
    {
      "date": "2025-05-01",
      "title": "8-K \u2014 Material Definitive Agreement \u00b7 Material Off-Balance-Sheet Obligation \u00b7 Other Events \u00b7 Financial Statements and Exhibits",
      "headline_ai": "",
      "snippet": "",
      "url": "https://www.sec.gov/Archives/edgar/data/1396440/000139644025000054/main-20250430.htm",
      "source": "edgar",
      "source_label": "SEC 8-K",
      "category": "capital-markets",
      "accession": "0001396440-25-000054"
    },
    {
      "date": "2025-04-25",
      "title": "8-K \u2014 Material Definitive Agreement \u00b7 Material Off-Balance-Sheet Obligation \u00b7 Other Events \u00b7 Financial Statements and Exhibits",
      "headline_ai": "",
      "snippet": "",
      "url": "https://www.sec.gov/Archives/edgar/data/1396440/000139644025000050/main-20250424.htm",
      "source": "edgar",
      "source_label": "SEC 8-K",
      "category": "capital-markets",
      "accession": "0001396440-25-000050"
    },
    {
      "date": "2025-04-16",
      "title": "8-K \u2014 Results of Operations \u00b7 Financial Statements and Exhibits",
      "headline_ai": "",
      "snippet": "",
      "url": "https://www.sec.gov/Archives/edgar/data/1396440/000139644025000045/main-20250416.htm",
      "source": "edgar",
      "source_label": "SEC 8-K",
      "category": "earnings",
      "accession": "0001396440-25-000045"
    },
    {
      "date": "2025-04-10",
      "title": "8-K \u2014 Results of Operations \u00b7 Financial Statements and Exhibits",
      "headline_ai": "",
      "snippet": "",
      "url": "https://www.sec.gov/Archives/edgar/data/1396440/000139644025000042/main-20250410.htm",
      "source": "edgar",
      "source_label": "SEC 8-K",
      "category": "earnings",
      "accession": "0001396440-25-000042"
    },
    {
      "date": "2025-03-05",
      "title": "8-K \u2014 Other Events \u00b7 Financial Statements and Exhibits",
      "headline_ai": "",
      "snippet": "",
      "url": "https://www.sec.gov/Archives/edgar/data/1396440/000139644025000033/main-20250304.htm",
      "source": "edgar",
      "source_label": "SEC 8-K",
      "category": "other",
      "accession": "0001396440-25-000033"
    },
    {
      "date": "2025-02-27",
      "title": "8-K \u2014 Results of Operations \u00b7 Financial Statements and Exhibits",
      "headline_ai": "",
      "snippet": "",
      "url": "https://www.sec.gov/Archives/edgar/data/1396440/000139644025000011/main-20250227.htm",
      "source": "edgar",
      "source_label": "SEC 8-K",
      "category": "earnings",
      "accession": "0001396440-25-000011"
    },
    {
      "date": "2025-02-25",
      "title": "8-K \u2014 Other Events \u00b7 Financial Statements and Exhibits",
      "headline_ai": "",
      "snippet": "",
      "url": "https://www.sec.gov/Archives/edgar/data/1396440/000139644025000009/main-20250225.htm",
      "source": "edgar",
      "source_label": "SEC 8-K",
      "category": "other",
      "accession": "0001396440-25-000009"
    },
    {
      "date": "2025-01-16",
      "title": "8-K \u2014 Results of Operations \u00b7 Financial Statements and Exhibits",
      "headline_ai": "",
      "snippet": "",
      "url": "https://www.sec.gov/Archives/edgar/data/1396440/000139644025000007/main-20250116.htm",
      "source": "edgar",
      "source_label": "SEC 8-K",
      "category": "earnings",
      "accession": "0001396440-25-000007"
    },
    {
      "date": "2025-01-10",
      "title": "8-K \u2014 Results of Operations \u00b7 Financial Statements and Exhibits",
      "headline_ai": "",
      "snippet": "",
      "url": "https://www.sec.gov/Archives/edgar/data/1396440/000139644025000002/main-20250109.htm",
      "source": "edgar",
      "source_label": "SEC 8-K",
      "category": "earnings",
      "accession": "0001396440-25-000002"
    },
    {
      "date": "2024-11-07",
      "title": "8-K \u2014 Results of Operations \u00b7 Financial Statements and Exhibits",
      "headline_ai": "",
      "snippet": "",
      "url": "https://www.sec.gov/Archives/edgar/data/1396440/000139644024000231/main-20241107.htm",
      "source": "edgar",
      "source_label": "SEC 8-K",
      "category": "earnings",
      "accession": "0001396440-24-000231"
    },
    {
      "date": "2024-11-05",
      "title": "8-K \u2014 Other Events \u00b7 Financial Statements and Exhibits",
      "headline_ai": "",
      "snippet": "",
      "url": "https://www.sec.gov/Archives/edgar/data/1396440/000139644024000228/main-20241105.htm",
      "source": "edgar",
      "source_label": "SEC 8-K",
      "category": "other",
      "accession": "0001396440-24-000228"
    },
    {
      "date": "2024-10-15",
      "title": "8-K \u2014 Results of Operations \u00b7 Financial Statements and Exhibits",
      "headline_ai": "",
      "snippet": "",
      "url": "https://www.sec.gov/Archives/edgar/data/1396440/000139644024000216/main-20241015.htm",
      "source": "edgar",
      "source_label": "SEC 8-K",
      "category": "earnings",
      "accession": "0001396440-24-000216"
    },
    {
      "date": "2024-10-10",
      "title": "8-K \u2014 Results of Operations \u00b7 Financial Statements and Exhibits",
      "headline_ai": "",
      "snippet": "",
      "url": "https://www.sec.gov/Archives/edgar/data/1396440/000139644024000214/main-20241010.htm",
      "source": "edgar",
      "source_label": "SEC 8-K",
      "category": "earnings",
      "accession": "0001396440-24-000214"
    },
    {
      "date": "2024-10-01",
      "title": "8-K \u2014 Material Definitive Agreement \u00b7 Material Off-Balance-Sheet Obligation \u00b7 Other Events \u00b7 Financial Statements and Exhibits",
      "headline_ai": "",
      "snippet": "",
      "url": "https://www.sec.gov/Archives/edgar/data/1396440/000139644024000207/main-20240926.htm",
      "source": "edgar",
      "source_label": "SEC 8-K",
      "category": "capital-markets",
      "accession": "0001396440-24-000207"
    },
    {
      "date": "2024-09-13",
      "title": "8-K \u2014 Material Definitive Agreement \u00b7 Material Off-Balance-Sheet Obligation \u00b7 Financial Statements and Exhibits",
      "headline_ai": "",
      "snippet": "",
      "url": "https://www.sec.gov/Archives/edgar/data/1396440/000139644024000197/main-20240911.htm",
      "source": "edgar",
      "source_label": "SEC 8-K",
      "category": "capital-markets",
      "accession": "0001396440-24-000197"
    },
    {
      "date": "2024-09-10",
      "title": "8-K \u2014 Regulation FD Disclosure \u00b7 Financial Statements and Exhibits",
      "headline_ai": "",
      "snippet": "",
      "url": "https://www.sec.gov/Archives/edgar/data/1396440/000139644024000163/main-20240910.htm",
      "source": "edgar",
      "source_label": "SEC 8-K",
      "category": "other",
      "accession": "0001396440-24-000163"
    },
    {
      "date": "2024-08-08",
      "title": "8-K \u2014 Results of Operations \u00b7 Financial Statements and Exhibits",
      "headline_ai": "",
      "snippet": "",
      "url": "https://www.sec.gov/Archives/edgar/data/1396440/000139644024000148/main-20240808.htm",
      "source": "edgar",
      "source_label": "SEC 8-K",
      "category": "earnings",
      "accession": "0001396440-24-000148"
    },
    {
      "date": "2024-08-06",
      "title": "8-K \u2014 Other Events \u00b7 Financial Statements and Exhibits",
      "headline_ai": "",
      "snippet": "",
      "url": "https://www.sec.gov/Archives/edgar/data/1396440/000139644024000141/main-20240806.htm",
      "source": "edgar",
      "source_label": "SEC 8-K",
      "category": "other",
      "accession": "0001396440-24-000141"
    },
    {
      "date": "2024-07-25",
      "title": "8-K \u2014 Regulation FD Disclosure \u00b7 Financial Statements and Exhibits",
      "headline_ai": "",
      "snippet": "",
      "url": "https://www.sec.gov/Archives/edgar/data/1396440/000139644024000137/main-20240725.htm",
      "source": "edgar",
      "source_label": "SEC 8-K",
      "category": "other",
      "accession": "0001396440-24-000137"
    },
    {
      "date": "2024-07-16",
      "title": "8-K \u2014 Results of Operations \u00b7 Financial Statements and Exhibits",
      "headline_ai": "",
      "snippet": "",
      "url": "https://www.sec.gov/Archives/edgar/data/1396440/000139644024000132/main-20240716.htm",
      "source": "edgar",
      "source_label": "SEC 8-K",
      "category": "earnings",
      "accession": "0001396440-24-000132"
    },
    {
      "date": "2024-07-11",
      "title": "8-K \u2014 Results of Operations \u00b7 Financial Statements and Exhibits",
      "headline_ai": "",
      "snippet": "",
      "url": "https://www.sec.gov/Archives/edgar/data/1396440/000139644024000130/main-20240711.htm",
      "source": "edgar",
      "source_label": "SEC 8-K",
      "category": "earnings",
      "accession": "0001396440-24-000130"
    },
    {
      "date": "2024-06-28",
      "title": "8-K \u2014 Material Definitive Agreement \u00b7 Material Off-Balance-Sheet Obligation \u00b7 Other Events \u00b7 Financial Statements and Exhibits",
      "headline_ai": "",
      "snippet": "",
      "url": "https://www.sec.gov/Archives/edgar/data/1396440/000139644024000126/main-20240627.htm",
      "source": "edgar",
      "source_label": "SEC 8-K",
      "category": "capital-markets",
      "accession": "0001396440-24-000126"
    },
    {
      "date": "2024-06-20",
      "title": "8-K \u2014 Regulation FD Disclosure",
      "headline_ai": "",
      "snippet": "",
      "url": "https://www.sec.gov/Archives/edgar/data/1396440/000139644024000122/main-20240620.htm",
      "source": "edgar",
      "source_label": "SEC 8-K",
      "category": "other",
      "accession": "0001396440-24-000122"
    },
    {
      "date": "2024-06-04",
      "title": "8-K \u2014 Material Definitive Agreement \u00b7 Material Off-Balance-Sheet Obligation \u00b7 Financial Statements and Exhibits",
      "headline_ai": "",
      "snippet": "",
      "url": "https://www.sec.gov/Archives/edgar/data/1396440/000139644024000116/main-20240604.htm",
      "source": "edgar",
      "source_label": "SEC 8-K",
      "category": "capital-markets",
      "accession": "0001396440-24-000116"
    },
    {
      "date": "2024-05-30",
      "title": "8-K \u2014 Material Definitive Agreement \u00b7 Material Off-Balance-Sheet Obligation \u00b7 Financial Statements and Exhibits",
      "headline_ai": "",
      "snippet": "",
      "url": "https://www.sec.gov/Archives/edgar/data/1396440/000139644024000114/main-20240526.htm",
      "source": "edgar",
      "source_label": "SEC 8-K",
      "category": "capital-markets",
      "accession": "0001396440-24-000114"
    },
    {
      "date": "2024-05-09",
      "title": "8-K \u2014 Results of Operations \u00b7 Financial Statements and Exhibits",
      "headline_ai": "",
      "snippet": "",
      "url": "https://www.sec.gov/Archives/edgar/data/1396440/000139644024000078/main-20240509.htm",
      "source": "edgar",
      "source_label": "SEC 8-K",
      "category": "earnings",
      "accession": "0001396440-24-000078"
    },
    {
      "date": "2024-05-07",
      "title": "8-K \u2014 Submission of Matters to a Vote",
      "headline_ai": "",
      "snippet": "",
      "url": "https://www.sec.gov/Archives/edgar/data/1396440/000139644024000073/main-20240506.htm",
      "source": "edgar",
      "source_label": "SEC 8-K",
      "category": "other",
      "accession": "0001396440-24-000073"
    },
    {
      "date": "2024-05-07",
      "title": "8-K \u2014 Other Events \u00b7 Financial Statements and Exhibits",
      "headline_ai": "",
      "snippet": "",
      "url": "https://www.sec.gov/Archives/edgar/data/1396440/000139644024000071/main-20240507.htm",
      "source": "edgar",
      "source_label": "SEC 8-K",
      "category": "other",
      "accession": "0001396440-24-000071"
    },
    {
      "date": "2024-04-16",
      "title": "8-K \u2014 Results of Operations \u00b7 Financial Statements and Exhibits",
      "headline_ai": "",
      "snippet": "",
      "url": "https://www.sec.gov/Archives/edgar/data/1396440/000139644024000068/main-20240416.htm",
      "source": "edgar",
      "source_label": "SEC 8-K",
      "category": "earnings",
      "accession": "0001396440-24-000068"
    },
    {
      "date": "2024-04-11",
      "title": "8-K \u2014 Results of Operations \u00b7 Financial Statements and Exhibits",
      "headline_ai": "",
      "snippet": "",
      "url": "https://www.sec.gov/Archives/edgar/data/1396440/000139644024000065/main-20240411.htm",
      "source": "edgar",
      "source_label": "SEC 8-K",
      "category": "earnings",
      "accession": "0001396440-24-000065"
    },
    {
      "date": "2024-02-22",
      "title": "8-K \u2014 Results of Operations \u00b7 Financial Statements and Exhibits",
      "headline_ai": "",
      "snippet": "",
      "url": "https://www.sec.gov/Archives/edgar/data/1396440/000139644024000050/main-20240222.htm",
      "source": "edgar",
      "source_label": "SEC 8-K",
      "category": "earnings",
      "accession": "0001396440-24-000050"
    },
    {
      "date": "2024-02-21",
      "title": "8-K \u2014 Other Events \u00b7 Financial Statements and Exhibits",
      "headline_ai": "",
      "snippet": "",
      "url": "https://www.sec.gov/Archives/edgar/data/1396440/000139644024000045/main-20240221.htm",
      "source": "edgar",
      "source_label": "SEC 8-K",
      "category": "other",
      "accession": "0001396440-24-000045"
    },
    {
      "date": "2024-01-17",
      "title": "8-K \u2014 Results of Operations \u00b7 Financial Statements and Exhibits",
      "headline_ai": "",
      "snippet": "",
      "url": "https://www.sec.gov/Archives/edgar/data/1396440/000139644024000042/main-20240117.htm",
      "source": "edgar",
      "source_label": "SEC 8-K",
      "category": "earnings",
      "accession": "0001396440-24-000042"
    },
    {
      "date": "2024-01-16",
      "title": "8-K \u2014 Results of Operations \u00b7 Financial Statements and Exhibits",
      "headline_ai": "",
      "snippet": "",
      "url": "https://www.sec.gov/Archives/edgar/data/1396440/000139644024000038/main-20240116.htm",
      "source": "edgar",
      "source_label": "SEC 8-K",
      "category": "earnings",
      "accession": "0001396440-24-000038"
    },
    {
      "date": "2024-01-12",
      "title": "8-K \u2014 Material Definitive Agreement \u00b7 Material Off-Balance-Sheet Obligation \u00b7 Financial Statements and Exhibits",
      "headline_ai": "",
      "snippet": "",
      "url": "https://www.sec.gov/Archives/edgar/data/1396440/000139644024000036/main-20240110.htm",
      "source": "edgar",
      "source_label": "SEC 8-K",
      "category": "capital-markets",
      "accession": "0001396440-24-000036"
    },
    {
      "date": "2023-11-02",
      "title": "8-K \u2014 Results of Operations \u00b7 Financial Statements and Exhibits",
      "headline_ai": "",
      "snippet": "",
      "url": "https://www.sec.gov/Archives/edgar/data/1396440/000139644023000137/main-20231102.htm",
      "source": "edgar",
      "source_label": "SEC 8-K",
      "category": "earnings",
      "accession": "0001396440-23-000137"
    },
    {
      "date": "2023-11-01",
      "title": "8-K \u2014 Other Events \u00b7 Financial Statements and Exhibits",
      "headline_ai": "",
      "snippet": "",
      "url": "https://www.sec.gov/Archives/edgar/data/1396440/000139644023000128/main-20231101.htm",
      "source": "edgar",
      "source_label": "SEC 8-K",
      "category": "other",
      "accession": "0001396440-23-000128"
    },
    {
      "date": "2023-10-17",
      "title": "8-K \u2014 Results of Operations \u00b7 Financial Statements and Exhibits",
      "headline_ai": "",
      "snippet": "",
      "url": "https://www.sec.gov/Archives/edgar/data/1396440/000139644023000122/main-20231017.htm",
      "source": "edgar",
      "source_label": "SEC 8-K",
      "category": "earnings",
      "accession": "0001396440-23-000122"
    },
    {
      "date": "2023-10-13",
      "title": "8-K \u2014 Material Definitive Agreement \u00b7 Material Off-Balance-Sheet Obligation \u00b7 Other Events \u00b7 Financial Statements and Exhibits",
      "headline_ai": "",
      "snippet": "",
      "url": "https://www.sec.gov/Archives/edgar/data/1396440/000139644023000118/main-20231012.htm",
      "source": "edgar",
      "source_label": "SEC 8-K",
      "category": "capital-markets",
      "accession": "0001396440-23-000118"
    },
    {
      "date": "2023-10-12",
      "title": "8-K \u2014 Material Definitive Agreement \u00b7 Material Off-Balance-Sheet Obligation \u00b7 Financial Statements and Exhibits",
      "headline_ai": "",
      "snippet": "",
      "url": "https://www.sec.gov/Archives/edgar/data/1396440/000139644023000115/main-20231005.htm",
      "source": "edgar",
      "source_label": "SEC 8-K",
      "category": "capital-markets",
      "accession": "0001396440-23-000115"
    },
    {
      "date": "2023-10-12",
      "title": "8-K \u2014 Results of Operations \u00b7 Financial Statements and Exhibits",
      "headline_ai": "",
      "snippet": "",
      "url": "https://www.sec.gov/Archives/edgar/data/1396440/000139644023000113/main-20231012.htm",
      "source": "edgar",
      "source_label": "SEC 8-K",
      "category": "earnings",
      "accession": "0001396440-23-000113"
    },
    {
      "date": "2023-08-03",
      "title": "8-K \u2014 Results of Operations \u00b7 Financial Statements and Exhibits",
      "headline_ai": "",
      "snippet": "",
      "url": "https://www.sec.gov/Archives/edgar/data/1396440/000139644023000097/main-20230803.htm",
      "source": "edgar",
      "source_label": "SEC 8-K",
      "category": "earnings",
      "accession": "0001396440-23-000097"
    },
    {
      "date": "2023-08-02",
      "title": "8-K \u2014 Results of Operations \u00b7 Financial Statements and Exhibits",
      "headline_ai": "",
      "snippet": "",
      "url": "https://www.sec.gov/Archives/edgar/data/1396440/000139644023000091/main-20230802.htm",
      "source": "edgar",
      "source_label": "SEC 8-K",
      "category": "earnings",
      "accession": "0001396440-23-000091"
    },
    {
      "date": "2023-07-18",
      "title": "8-K \u2014 Results of Operations \u00b7 Financial Statements and Exhibits",
      "headline_ai": "",
      "snippet": "",
      "url": "https://www.sec.gov/Archives/edgar/data/1396440/000139644023000084/main-20230718.htm",
      "source": "edgar",
      "source_label": "SEC 8-K",
      "category": "earnings",
      "accession": "0001396440-23-000084"
    },
    {
      "date": "2023-07-13",
      "title": "8-K \u2014 Results of Operations \u00b7 Financial Statements and Exhibits",
      "headline_ai": "",
      "snippet": "",
      "url": "https://www.sec.gov/Archives/edgar/data/1396440/000139644023000080/main-20230713.htm",
      "source": "edgar",
      "source_label": "SEC 8-K",
      "category": "earnings",
      "accession": "0001396440-23-000080"
    },
    {
      "date": "2023-06-22",
      "title": "8-K \u2014 Regulation FD Disclosure",
      "headline_ai": "",
      "snippet": "",
      "url": "https://www.sec.gov/Archives/edgar/data/1396440/000139644023000077/main-20230622.htm",
      "source": "edgar",
      "source_label": "SEC 8-K",
      "category": "other",
      "accession": "0001396440-23-000077"
    },
    {
      "date": "2023-06-01",
      "title": "8-K \u2014 Material Definitive Agreement \u00b7 Termination of Material Agreement \u00b7 Financial Statements and Exhibits",
      "headline_ai": "",
      "snippet": "",
      "url": "https://www.sec.gov/Archives/edgar/data/1396440/000139644023000073/main-20230531.htm",
      "source": "edgar",
      "source_label": "SEC 8-K",
      "category": "credit-event",
      "accession": "0001396440-23-000073"
    },
    {
      "date": "2023-05-04",
      "title": "8-K \u2014 Results of Operations \u00b7 Financial Statements and Exhibits",
      "headline_ai": "",
      "snippet": "",
      "url": "https://www.sec.gov/Archives/edgar/data/1396440/000139644023000063/main-20230504.htm",
      "source": "edgar",
      "source_label": "SEC 8-K",
      "category": "earnings",
      "accession": "0001396440-23-000063"
    },
    {
      "date": "2023-05-02",
      "title": "8-K \u2014 Submission of Matters to a Vote \u00b7 Other Events \u00b7 Financial Statements and Exhibits",
      "headline_ai": "",
      "snippet": "",
      "url": "https://www.sec.gov/Archives/edgar/data/1396440/000139644023000056/main-20230501.htm",
      "source": "edgar",
      "source_label": "SEC 8-K",
      "category": "other",
      "accession": "0001396440-23-000056"
    },
    {
      "date": "2023-04-18",
      "title": "8-K \u2014 Results of Operations \u00b7 Financial Statements and Exhibits",
      "headline_ai": "",
      "snippet": "",
      "url": "https://www.sec.gov/Archives/edgar/data/1396440/000139644023000053/main-20230418.htm",
      "source": "edgar",
      "source_label": "SEC 8-K",
      "category": "earnings",
      "accession": "0001396440-23-000053"
    },
    {
      "date": "2023-04-12",
      "title": "8-K \u2014 Results of Operations \u00b7 Financial Statements and Exhibits",
      "headline_ai": "",
      "snippet": "",
      "url": "https://www.sec.gov/Archives/edgar/data/1396440/000139644023000050/main-20230412.htm",
      "source": "edgar",
      "source_label": "SEC 8-K",
      "category": "earnings",
      "accession": "0001396440-23-000050"
    },
    {
      "date": "2023-03-20",
      "title": "8-K \u2014 Officer / Director Departure or Appointment \u00b7 Financial Statements and Exhibits",
      "headline_ai": "",
      "snippet": "",
      "url": "https://www.sec.gov/Archives/edgar/data/1396440/000139644023000046/main-20230320.htm",
      "source": "edgar",
      "source_label": "SEC 8-K",
      "category": "personnel",
      "accession": "0001396440-23-000046"
    },
    {
      "date": "2023-03-14",
      "title": "8-K \u2014 Regulation FD Disclosure \u00b7 Financial Statements and Exhibits",
      "headline_ai": "",
      "snippet": "",
      "url": "https://www.sec.gov/Archives/edgar/data/1396440/000139644023000042/main-20230313.htm",
      "source": "edgar",
      "source_label": "SEC 8-K",
      "category": "other",
      "accession": "0001396440-23-000042"
    },
    {
      "date": "2023-02-23",
      "title": "8-K \u2014 Results of Operations \u00b7 Financial Statements and Exhibits",
      "headline_ai": "",
      "snippet": "",
      "url": "https://www.sec.gov/Archives/edgar/data/1396440/000139644023000030/main-20230223.htm",
      "source": "edgar",
      "source_label": "SEC 8-K",
      "category": "earnings",
      "accession": "0001396440-23-000030"
    },
    {
      "date": "2023-02-22",
      "title": "8-K \u2014 Other Events \u00b7 Financial Statements and Exhibits",
      "headline_ai": "",
      "snippet": "",
      "url": "https://www.sec.gov/Archives/edgar/data/1396440/000139644023000018/main-20230222.htm",
      "source": "edgar",
      "source_label": "SEC 8-K",
      "category": "other",
      "accession": "0001396440-23-000018"
    },
    {
      "date": "2023-02-02",
      "title": "8-K \u2014 Other Events \u00b7 Financial Statements and Exhibits",
      "headline_ai": "",
      "snippet": "",
      "url": "https://www.sec.gov/Archives/edgar/data/1396440/000139644023000014/main-20230202.htm",
      "source": "edgar",
      "source_label": "SEC 8-K",
      "category": "other",
      "accession": "0001396440-23-000014"
    },
    {
      "date": "2023-01-18",
      "title": "8-K \u2014 Material Definitive Agreement \u00b7 Material Off-Balance-Sheet Obligation \u00b7 Other Events \u00b7 Financial Statements and Exhibits",
      "headline_ai": "",
      "snippet": "",
      "url": "https://www.sec.gov/Archives/edgar/data/1396440/000139644023000008/main-20230113.htm",
      "source": "edgar",
      "source_label": "SEC 8-K",
      "category": "capital-markets",
      "accession": "0001396440-23-000008"
    },
    {
      "date": "2023-01-17",
      "title": "8-K \u2014 Results of Operations \u00b7 Financial Statements and Exhibits",
      "headline_ai": "",
      "snippet": "",
      "url": "https://www.sec.gov/Archives/edgar/data/1396440/000139644023000006/main-20230117.htm",
      "source": "edgar",
      "source_label": "SEC 8-K",
      "category": "earnings",
      "accession": "0001396440-23-000006"
    },
    {
      "date": "2023-01-12",
      "title": "8-K \u2014 Results of Operations \u00b7 Financial Statements and Exhibits",
      "headline_ai": "",
      "snippet": "",
      "url": "https://www.sec.gov/Archives/edgar/data/1396440/000139644023000004/main-20230112.htm",
      "source": "edgar",
      "source_label": "SEC 8-K",
      "category": "earnings",
      "accession": "0001396440-23-000004"
    },
    {
      "date": "2022-12-28",
      "title": "8-K \u2014 Material Definitive Agreement \u00b7 Material Off-Balance-Sheet Obligation \u00b7 Other Events \u00b7 Financial Statements and Exhibits",
      "headline_ai": "",
      "snippet": "",
      "url": "https://www.sec.gov/Archives/edgar/data/1396440/000139644022000051/main-20221222.htm",
      "source": "edgar",
      "source_label": "SEC 8-K",
      "category": "capital-markets",
      "accession": "0001396440-22-000051"
    },
    {
      "date": "2022-12-15",
      "title": "8-K \u2014 Officer / Director Departure or Appointment",
      "headline_ai": "",
      "snippet": "",
      "url": "https://www.sec.gov/Archives/edgar/data/1396440/000139644022000048/main-20221214.htm",
      "source": "edgar",
      "source_label": "SEC 8-K",
      "category": "personnel",
      "accession": "0001396440-22-000048"
    },
    {
      "date": "2022-12-06",
      "title": "8-K \u2014 Material Definitive Agreement \u00b7 Material Off-Balance-Sheet Obligation \u00b7 Financial Statements and Exhibits",
      "headline_ai": "",
      "snippet": "",
      "url": "https://www.sec.gov/Archives/edgar/data/1396440/000139644022000045/main-20221206.htm",
      "source": "edgar",
      "source_label": "SEC 8-K",
      "category": "capital-markets",
      "accession": "0001396440-22-000045"
    },
    {
      "date": "2022-11-28",
      "title": "8-K \u2014 Material Definitive Agreement \u00b7 Material Off-Balance-Sheet Obligation \u00b7 Other Events \u00b7 Financial Statements and Exhibits",
      "headline_ai": "",
      "snippet": "",
      "url": "https://www.sec.gov/Archives/edgar/data/1396440/000139644022000043/main-20221122.htm",
      "source": "edgar",
      "source_label": "SEC 8-K",
      "category": "capital-markets",
      "accession": "0001396440-22-000043"
    },
    {
      "date": "2022-11-03",
      "title": "8-K \u2014 Results of Operations \u00b7 Financial Statements and Exhibits",
      "headline_ai": "",
      "snippet": "",
      "url": "https://www.sec.gov/Archives/edgar/data/1396440/000156459022036620/main-8k_20221103.htm",
      "source": "edgar",
      "source_label": "SEC 8-K",
      "category": "earnings",
      "accession": "0001564590-22-036620"
    },
    {
      "date": "2022-11-02",
      "title": "8-K \u2014 Other Events \u00b7 Financial Statements and Exhibits",
      "headline_ai": "",
      "snippet": "",
      "url": "https://www.sec.gov/Archives/edgar/data/1396440/000139644022000031/main-20221102.htm",
      "source": "edgar",
      "source_label": "SEC 8-K",
      "category": "other",
      "accession": "0001396440-22-000031"
    },
    {
      "date": "2022-10-18",
      "title": "8-K \u2014 Results of Operations \u00b7 Financial Statements and Exhibits",
      "headline_ai": "",
      "snippet": "",
      "url": "https://www.sec.gov/Archives/edgar/data/1396440/000139644022000028/main-20221018.htm",
      "source": "edgar",
      "source_label": "SEC 8-K",
      "category": "earnings",
      "accession": "0001396440-22-000028"
    },
    {
      "date": "2022-10-14",
      "title": "8-K \u2014 Results of Operations \u00b7 Financial Statements and Exhibits",
      "headline_ai": "",
      "snippet": "",
      "url": "https://www.sec.gov/Archives/edgar/data/1396440/000139644022000026/main-20221014.htm",
      "source": "edgar",
      "source_label": "SEC 8-K",
      "category": "earnings",
      "accession": "0001396440-22-000026"
    },
    {
      "date": "2022-08-15",
      "title": "8-K \u2014 Material Definitive Agreement \u00b7 Financial Statements and Exhibits",
      "headline_ai": "",
      "snippet": "",
      "url": "https://www.sec.gov/Archives/edgar/data/1396440/000139644022000023/main-20220811x8k.htm",
      "source": "edgar",
      "source_label": "SEC 8-K",
      "category": "capital-markets",
      "accession": "0001396440-22-000023"
    },
    {
      "date": "2022-08-04",
      "title": "8-K \u2014 Material Definitive Agreement \u00b7 Results of Operations \u00b7 Material Off-Balance-Sheet Obligation \u00b7 Regulation FD Disclosure \u00b7 Financial Statements and Exhibits",
      "headline_ai": "",
      "snippet": "",
      "url": "https://www.sec.gov/Archives/edgar/data/1396440/000139644022000012/tmb-20220804x8k.htm",
      "source": "edgar",
      "source_label": "SEC 8-K",
      "category": "earnings",
      "accession": "0001396440-22-000012"
    },
    {
      "date": "2022-08-02",
      "title": "8-K \u2014 Other Events \u00b7 Financial Statements and Exhibits",
      "headline_ai": "",
      "snippet": "",
      "url": "https://www.sec.gov/Archives/edgar/data/1396440/000139644022000010/tmb-20220802x8k.htm",
      "source": "edgar",
      "source_label": "SEC 8-K",
      "category": "other",
      "accession": "0001396440-22-000010"
    },
    {
      "date": "2022-07-14",
      "title": "8-K \u2014 Results of Operations \u00b7 Other Events \u00b7 Financial Statements and Exhibits",
      "headline_ai": "",
      "snippet": "",
      "url": "https://www.sec.gov/Archives/edgar/data/1396440/000139644022000008/main-20220713x8k.htm",
      "source": "edgar",
      "source_label": "SEC 8-K",
      "category": "earnings",
      "accession": "0001396440-22-000008"
    },
    {
      "date": "2022-06-23",
      "title": "8-K \u2014 Regulation FD Disclosure",
      "headline_ai": "",
      "snippet": "",
      "url": "https://www.sec.gov/Archives/edgar/data/1396440/000155837022010218/main-20220623x8k.htm",
      "source": "edgar",
      "source_label": "SEC 8-K",
      "category": "other",
      "accession": "0001558370-22-010218"
    },
    {
      "date": "2022-05-05",
      "title": "8-K \u2014 Results of Operations \u00b7 Financial Statements and Exhibits",
      "headline_ai": "",
      "snippet": "",
      "url": "https://www.sec.gov/Archives/edgar/data/1396440/000156459022018321/main-8k_20220505.htm",
      "source": "edgar",
      "source_label": "SEC 8-K",
      "category": "earnings",
      "accession": "0001564590-22-018321"
    },
    {
      "date": "2022-05-03",
      "title": "8-K \u2014 Submission of Matters to a Vote \u00b7 Other Events \u00b7 Financial Statements and Exhibits",
      "headline_ai": "",
      "snippet": "",
      "url": "https://www.sec.gov/Archives/edgar/data/1396440/000155837022006827/main-20220502x8k.htm",
      "source": "edgar",
      "source_label": "SEC 8-K",
      "category": "other",
      "accession": "0001558370-22-006827"
    },
    {
      "date": "2022-04-14",
      "title": "8-K \u2014 Results of Operations \u00b7 Financial Statements and Exhibits",
      "headline_ai": "",
      "snippet": "",
      "url": "https://www.sec.gov/Archives/edgar/data/1396440/000155837022005417/main-20220414x8k.htm",
      "source": "edgar",
      "source_label": "SEC 8-K",
      "category": "earnings",
      "accession": "0001558370-22-005417"
    },
    {
      "date": "2022-03-04",
      "title": "8-K \u2014 Other Events \u00b7 Financial Statements and Exhibits",
      "headline_ai": "",
      "snippet": "",
      "url": "https://www.sec.gov/Archives/edgar/data/1396440/000155837022002854/tmb-20220303x8k.htm",
      "source": "edgar",
      "source_label": "SEC 8-K",
      "category": "other",
      "accession": "0001558370-22-002854"
    },
    {
      "date": "2022-02-28",
      "title": "8-K \u2014 Other Events \u00b7 Financial Statements and Exhibits",
      "headline_ai": "",
      "snippet": "",
      "url": "https://www.sec.gov/Archives/edgar/data/1396440/000155837022002275/main-20220223x8k.htm",
      "source": "edgar",
      "source_label": "SEC 8-K",
      "category": "other",
      "accession": "0001558370-22-002275"
    },
    {
      "date": "2022-02-25",
      "title": "8-K \u2014 Results of Operations \u00b7 Financial Statements and Exhibits",
      "headline_ai": "",
      "snippet": "",
      "url": "https://www.sec.gov/Archives/edgar/data/1396440/000156459022006863/main-8k_20220224.htm",
      "source": "edgar",
      "source_label": "SEC 8-K",
      "category": "earnings",
      "accession": "0001564590-22-006863"
    },
    {
      "date": "2022-02-24",
      "title": "8-K \u2014 Other Events \u00b7 Financial Statements and Exhibits",
      "headline_ai": "",
      "snippet": "",
      "url": "https://www.sec.gov/Archives/edgar/data/1396440/000155837022001827/tmb-20220224x8k.htm",
      "source": "edgar",
      "source_label": "SEC 8-K",
      "category": "other",
      "accession": "0001558370-22-001827"
    },
    {
      "date": "2022-01-19",
      "title": "8-K \u2014 Results of Operations \u00b7 Financial Statements and Exhibits",
      "headline_ai": "",
      "snippet": "",
      "url": "https://www.sec.gov/Archives/edgar/data/1396440/000155837022000295/main-20220119x8k.htm",
      "source": "edgar",
      "source_label": "SEC 8-K",
      "category": "earnings",
      "accession": "0001558370-22-000295"
    },
    {
      "date": "2022-01-11",
      "title": "8-K \u2014 Results of Operations \u00b7 Financial Statements and Exhibits",
      "headline_ai": "",
      "snippet": "",
      "url": "https://www.sec.gov/Archives/edgar/data/1396440/000155837022000202/main-20220111x8k.htm",
      "source": "edgar",
      "source_label": "SEC 8-K",
      "category": "earnings",
      "accession": "0001558370-22-000202"
    },
    {
      "date": "2021-11-12",
      "title": "8-K \u2014 Material Definitive Agreement \u00b7 Financial Statements and Exhibits",
      "headline_ai": "",
      "snippet": "",
      "url": "https://www.sec.gov/Archives/edgar/data/1396440/000155837021015599/main-20211111x8k.htm",
      "source": "edgar",
      "source_label": "SEC 8-K",
      "category": "capital-markets",
      "accession": "0001558370-21-015599"
    },
    {
      "date": "2021-11-05",
      "title": "8-K \u2014 Results of Operations \u00b7 Financial Statements and Exhibits",
      "headline_ai": "",
      "snippet": "",
      "url": "https://www.sec.gov/Archives/edgar/data/1396440/000156459021054643/main-8k_20211104.htm",
      "source": "edgar",
      "source_label": "SEC 8-K",
      "category": "earnings",
      "accession": "0001564590-21-054643"
    },
    {
      "date": "2021-11-02",
      "title": "8-K \u2014 Other Events \u00b7 Financial Statements and Exhibits",
      "headline_ai": "",
      "snippet": "",
      "url": "https://www.sec.gov/Archives/edgar/data/1396440/000155837021013988/main-20211102x8k.htm",
      "source": "edgar",
      "source_label": "SEC 8-K",
      "category": "other",
      "accession": "0001558370-21-013988"
    },
    {
      "date": "2021-10-19",
      "title": "8-K \u2014 Results of Operations \u00b7 Financial Statements and Exhibits",
      "headline_ai": "",
      "snippet": "",
      "url": "https://www.sec.gov/Archives/edgar/data/1396440/000155837021013286/main-20211019x8k.htm",
      "source": "edgar",
      "source_label": "SEC 8-K",
      "category": "earnings",
      "accession": "0001558370-21-013286"
    },
    {
      "date": "2021-09-30",
      "title": "8-K \u2014 Material Definitive Agreement \u00b7 Material Off-Balance-Sheet Obligation \u00b7 Financial Statements and Exhibits",
      "headline_ai": "",
      "snippet": "",
      "url": "https://www.sec.gov/Archives/edgar/data/1396440/000155837021012892/tmb-20210928x8k.htm",
      "source": "edgar",
      "source_label": "SEC 8-K",
      "category": "capital-markets",
      "accession": "0001558370-21-012892"
    },
    {
      "date": "2021-08-06",
      "title": "8-K \u2014 Results of Operations \u00b7 Financial Statements and Exhibits",
      "headline_ai": "",
      "snippet": "",
      "url": "https://www.sec.gov/Archives/edgar/data/1396440/000156459021041754/main-8k_20210805.htm",
      "source": "edgar",
      "source_label": "SEC 8-K",
      "category": "earnings",
      "accession": "0001564590-21-041754"
    },
    {
      "date": "2021-08-03",
      "title": "8-K \u2014 Other Events \u00b7 Financial Statements and Exhibits",
      "headline_ai": "",
      "snippet": "",
      "url": "https://www.sec.gov/Archives/edgar/data/1396440/000155837021009863/tmb-20210803x8k.htm",
      "source": "edgar",
      "source_label": "SEC 8-K",
      "category": "other",
      "accession": "0001558370-21-009863"
    },
    {
      "date": "2021-07-15",
      "title": "8-K \u2014 Results of Operations \u00b7 Financial Statements and Exhibits",
      "headline_ai": "",
      "snippet": "",
      "url": "https://www.sec.gov/Archives/edgar/data/1396440/000155837021008925/main-20210715x8k.htm",
      "source": "edgar",
      "source_label": "SEC 8-K",
      "category": "earnings",
      "accession": "0001558370-21-008925"
    }
  ]
}